{"features":[{"type":"Feature","geometry":{"type":"Point","coordinates":[45.13859110019951,65.32905639866681]},"properties":{"city":null,"house":null,"id":1767,"name":"Памятик Павшим Воинам","post":null,"street":null,"x":45.138591100199505,"y":65.32905639866681}}],"type":"FeatureCollection"}