{"features":[{"type":"Feature","geometry":{"type":"Point","coordinates":[40.958257100431354,64.38371399978291]},"properties":{"city":null,"house":null,"id":1693,"name":"Вечная память героям павшим в боях за Родину 1941-45 гг.","post":null,"street":null,"x":40.958257100431354,"y":64.3837139997829}}],"type":"FeatureCollection"}