{"features":[{"type":"Feature","geometry":{"type":"Point","coordinates":[40.64727959996575,64.65941969946195]},"properties":{"city":null,"house":null,"id":1727,"name":"придорожный крест","post":null,"street":null,"x":40.64727959996574,"y":64.65941969946195}}],"type":"FeatureCollection"}