{"features":[{"type":"Feature","geometry":{"type":"Point","coordinates":[40.45730843993526,64.78271177007952]},"properties":{"city":"Лапоминка (Приморский район)","house":"18","id":7611,"name":"Айсберг, гостевой дом","post":"163029","street":"Лапоминка деревня","x":40.45730844,"y":64.78271177}},{"type":"Feature","geometry":{"type":"Point","coordinates":[40.45730843993526,64.78271177007952]},"properties":{"city":"Лапоминка (Приморский район)","house":"18","id":7894,"name":"Тайники Севера, мини-дома","post":"163029","street":"Лапоминка деревня","x":40.45730844,"y":64.78271177}}],"type":"FeatureCollection"}