{"features":[{"type":"Feature","geometry":{"type":"Point","coordinates":[40.800810299560254,64.48135719961323]},"properties":{"city":null,"house":null,"id":1701,"name":"Въездной знак-символ \"город Архангельск\" км. 16+000 автодороги Архангельск-Белогорский-Пинега-Кимжа-Мезень","post":null,"street":null,"x":40.80081029956026,"y":64.48135719961323}},{"type":"Feature","geometry":{"type":"Point","coordinates":[40.84807722974928,64.47723404992695]},"properties":{"city":"Уемский (Приморский район)","house":"7","id":7011,"name":"Музей народных промыслов и ремесел Приморья","post":"163502","street":"Заводская","x":40.84807723,"y":64.47723405}}],"type":"FeatureCollection"}