{"features":[{"type":"Feature","geometry":{"type":"Point","coordinates":[40.8942322899583,64.2932148000055]},"properties":{"city":"Беломорье (Приморский район)","house":"22","id":9231,"name":"Ла Багатель, загородный клуб","post":"163534","street":"Беломорье посёлок","x":40.89423229,"y":64.2932148}}],"type":"FeatureCollection"}