{"features":[{"type":"Feature","geometry":{"type":"Point","coordinates":[45.579453099749415,65.14217589885128]},"properties":{"city":null,"house":null,"id":1765,"name":"придорожный крест","post":null,"street":null,"x":45.57945309974942,"y":65.14217589885125}}],"type":"FeatureCollection"}