{"features":[{"type":"Feature","geometry":{"type":"Point","coordinates":[40.86427353000004,64.47375331000006]},"properties":{"city":"Уемский (Приморский район)","cpi_id":588466,"house":"60","id":18593,"name":"Приморская центральная районная больница, ГБУЗ","post":"163502","street":"Большесельская","x":40.86427353,"y":64.47375331}}],"type":"FeatureCollection"}