{"features":[{"type":"Feature","geometry":{"type":"Point","coordinates":[44.426516900000166,64.00661890000003]},"properties":{"city":"","cpi_id":7397,"house":"","id":196130,"name":"Центр здоровья","post":"","street":"","x":44.4265169,"y":64.0066189}}],"type":"FeatureCollection"}