{"features":[{"type":"Feature","geometry":{"type":"Point","coordinates":[45.52440500000011,63.609196200000014]},"properties":{"city":"","house":"","id":199345,"name":"Школа","post":"","street":"","x":45.524405,"y":63.6091962}}],"type":"FeatureCollection"}